paica/__init__.py
paica/core.py
paica-0.1.0.dist-info/licenses/LICENSE
paica-0.1.0.dist-info/METADATA
paica-0.1.0.dist-info/WHEEL
paica-0.1.0.dist-info/top_level.txt
paica-0.1.0.dist-info/RECORD
